setup.py
naganami_mqtt/__init__.py
naganami_mqtt/awsiot.py
naganami_mqtt/job.py
naganami_mqtt/mqtt_base.py
naganami_mqtt.egg-info/PKG-INFO
naganami_mqtt.egg-info/SOURCES.txt
naganami_mqtt.egg-info/dependency_links.txt
naganami_mqtt.egg-info/requires.txt
naganami_mqtt.egg-info/top_level.txt