Metadata-Version: 1.0
Name: naganami-mqtt
Version: 0.0.6
Summary: naganami sama type mqtt controller
Home-page: https://github.com/nc30/naganami_mqtt
Author: Himura Asahi
Author-email: himura@nitolab.com
License: UNKNOWN
Platform: UNKNOWN
